atomic/__init__.py
atomic/atomic.py
atomic/sample.py
pyatomic-0.0.2.dist-info/LICENSE
pyatomic-0.0.2.dist-info/METADATA
pyatomic-0.0.2.dist-info/WHEEL
pyatomic-0.0.2.dist-info/top_level.txt
pyatomic-0.0.2.dist-info/RECORD
