Metadata-Version: 2.1
Name: pyatomic
Version: 0.0.2
Summary: Atomic makes your code thread safe
Home-page: https://github.com/kr-g/pyatomic
Author: k.r. goger
Author-email: k.r.goger+pyatomic@gmail.com
License: MIT
Keywords: python threading lock sequence
Platform: UNKNOWN
Classifier: Development Status :: 3 - Alpha
Classifier: Operating System :: POSIX :: Linux
Classifier: Intended Audience :: Developers
Classifier: Programming Language :: Python :: 3
Classifier: License :: OSI Approved :: MIT License
Requires-Python: >=3.6
